quantdata_sdk/__init__.py
quantdata_sdk/__version__.py
quantdata_sdk/api.py
quantdata_sdk/constants.py
quantdata_sdk/entry_points.py
quantdata_sdk/response.py
quantdata_sdk/utils.py
quant_data_sdk-0.2.3.dist-info/LICENSE
quant_data_sdk-0.2.3.dist-info/METADATA
quant_data_sdk-0.2.3.dist-info/WHEEL
quant_data_sdk-0.2.3.dist-info/entry_points.txt
quant_data_sdk-0.2.3.dist-info/top_level.txt
quant_data_sdk-0.2.3.dist-info/RECORD
