Metadata-Version: 2.1
Name: quant-data-sdk
Version: 0.2.3
Summary: quant-data-sdk - sdk for quant data project
Home-page: UNKNOWN
Author: Rafał Niewiński
Author-email: rafalniewinski95@gmail.com
License: Apache 2.0
Keywords: quantdata sdk
Platform: UNKNOWN
Classifier: Development Status :: 4 - Beta
Classifier: Intended Audience :: Developers
Classifier: Programming Language :: Python :: 3.7
Requires-Python: >=3.7.*
Requires-Dist: numpy
Requires-Dist: requests
